{
  "850": [
    {
      "percent": 100,
      "minToDrop": "1",
      "maxToDrop": "1",
      "id": "4735",
      "differentItemsToDropRange": 1,
      "destructibleComponents": [
        {
          "name": "NJ - Skeleton Blacksmith",
          "objectID": 14024,
          "displayName": "Skeleton Blacksmith"
        }
      ],
      "soldByVendor": 1
    },
    {
      "percent": 100,
      "minToDrop": "1",
      "maxToDrop": "1",
      "id": "4735",
      "differentItemsToDropRange": 1,
      "destructibleComponents": [
        {
          "name": "NJ - Skeleton Blacksmith",
          "objectID": 14024,
          "displayName": "Skeleton Blacksmith"
        }
      ],
      "soldByVendor": 1
    }
  ]
}