{
  "547": [
    {
      "percent": 100,
      "minToDrop": "2",
      "maxToDrop": "2",
      "id": "2244",
      "differentItemsToDropRange": 1,
      "destructibleComponents": [],
      "soldByVendor": 0
    }
  ],
  "550": [
    {
      "percent": 100,
      "minToDrop": "2",
      "maxToDrop": "2",
      "id": "2244",
      "differentItemsToDropRange": 1,
      "destructibleComponents": [],
      "soldByVendor": 0
    }
  ],
  "805": [
    {
      "percent": 100,
      "minToDrop": "1",
      "maxToDrop": "0",
      "id": "4438",
      "differentItemsToDropRange": 74,
      "destructibleComponents": [],
      "soldByVendor": 0
    }
  ]
}