{
  "itemID": 13097,
  "name": "CP Loot Surprise Pack",
  "displayName": "Premium Surprise Pack",
  "description": "Double-click to use!",
  "iconURL": "https://xiphoseer.github.io/lu-res/textures/ui/inventory/presents/bag_red_black.png",
  "table": [
    {
      "missionID": "1888",
      "name": "Solo Riders",
      "objective": "As a solo player, defeat the 4 Riders in the Battle of Nimbus Station."
    },
    {
      "missionID": "1974",
      "name": "Bone Up",
      "objective": "Quick Build 75 more Skeleton Bouncers on the Ninjago Battlefield."
    }
  ]
}